atomicwriter-0.3.0.dist-info/RECORD
atomicwriter-0.3.0.dist-info/WHEEL
atomicwriter-0.3.0.dist-info/METADATA
atomicwriter-0.3.0.dist-info/licenses/LICENSE-APACHE
atomicwriter-0.3.0.dist-info/licenses/LICENSE-MIT
atomicwriter/__init__.pyi
atomicwriter/__init__.py
atomicwriter/_impl.cpython-39-darwin.so
atomicwriter/py.typed
